README
setup.py
PyRadbas.egg-info/PKG-INFO
PyRadbas.egg-info/SOURCES.txt
PyRadbas.egg-info/dependency_links.txt
PyRadbas.egg-info/requires.txt
PyRadbas.egg-info/top_level.txt
PyRadbas.egg-info/zip-safe
pyradbas/__init__.py
pyradbas/mlab.py
pyradbas/rbfn.py
pyradbas/train_exact.py
pyradbas/train_ols.py