Metadata-Version: 1.0
Name: PyRadbas
Version: 0.1.0
Summary: Simple Radial Basis Function Networks in Python
Home-page: http://cybercase.github.com/pyradbas/
Author: Stefano Brilli
Author-email: stefanobrilli@gmail.com
License: FreeBSD
Keywords: radial,basis,function,matlab,RBF,RBFN
Platform: UNKNOWN
Classifier: Development Status :: 4 - Beta
Classifier: Intended Audience :: Developers
Classifier: Intended Audience :: Science/Research
Classifier: Intended Audience :: Education
Classifier: License :: OSI Approved :: BSD License
Classifier: Natural Language :: English
Classifier: Programming Language :: Python
Classifier: Topic :: Scientific/Engineering :: Artificial Intelligence
Classifier: Topic :: Software Development :: Libraries :: Python Modules
Classifier: Operating System :: POSIX :: Linux
Classifier: Operating System :: MacOS :: MacOS X
Classifier: Operating System :: Microsoft :: Windows
